shopee_cmd/__init__.py
shopee_cmd/hello.py
shopee_cmd/import_bins.py
shopee_cmd-0.0.2.dist-info/LICENSE
shopee_cmd-0.0.2.dist-info/METADATA
shopee_cmd-0.0.2.dist-info/WHEEL
shopee_cmd-0.0.2.dist-info/entry_points.txt
shopee_cmd-0.0.2.dist-info/top_level.txt
shopee_cmd-0.0.2.dist-info/RECORD
