Metadata-Version: 2.1
Name: shopee-cmd
Version: 0.0.2
Summary: Shopee command line tools
Home-page: https://gitlab.com/garena-shopee/cmd
Author: jiao.xue
Author-email: jiao.xuejiao@gmail.com
License: UNKNOWN
Platform: UNKNOWN
Classifier: Programming Language :: Python :: 2
Classifier: License :: OSI Approved :: MIT License
Classifier: Operating System :: OS Independent
Requires-Dist: Click
